vnpy_ib/__init__.py
vnpy_ib/ib_gateway.py
vnpy_ib-10.40.1.2.dist-info/METADATA
vnpy_ib-10.40.1.2.dist-info/WHEEL
vnpy_ib-10.40.1.2.dist-info/licenses/LICENSE
vnpy_ib-10.40.1.2.dist-info/RECORD
