Metadata-Version: 2.4
Name: vnpy_ib
Version: 10.40.1.2
Summary: IB gateway for VeighNa quant trading framework.
Project-URL: Homepage, https://www.vnpy.com
Project-URL: Documentation, https://www.vnpy.com/docs
Project-URL: Source, https://github.com/vnpy/vnpy_ib/
Project-URL: Forum, https://www.vnpy.com/forum
Author-email: Xiaoyou Chen <xiaoyou.chen@mail.vnpy.com>
License: MIT
License-File: LICENSE
Keywords: algotrading,investment,quant,quantitative,trading
Classifier: Development Status :: 5 - Production/Stable
Classifier: License :: OSI Approved :: MIT License
Classifier: Natural Language :: Chinese (Simplified)
Classifier: Operating System :: OS Independent
Classifier: Programming Language :: Python :: 3
Classifier: Programming Language :: Python :: 3.10
Classifier: Programming Language :: Python :: 3.11
Classifier: Programming Language :: Python :: 3.12
Classifier: Programming Language :: Python :: 3.13
Classifier: Programming Language :: Python :: Implementation :: CPython
Classifier: Topic :: Office/Business :: Financial :: Investment
Requires-Python: >=3.10
Requires-Dist: protobuf==5.29.3
